zpickle/__init__.py
zpickle/_version.py
zpickle/compat.py
zpickle/config.py
zpickle/core.py
zpickle/exceptions.py
zpickle/format.py
zpickle-1.2.0.dist-info/licenses/LICENSE
zpickle-1.2.0.dist-info/METADATA
zpickle-1.2.0.dist-info/WHEEL
zpickle-1.2.0.dist-info/top_level.txt
zpickle-1.2.0.dist-info/RECORD
