Metadata-Version: 2.4
Name: zpickle
Version: 1.2.0
Summary: Transparent, drop-in compression for Python's pickle — smaller files, same API
Author: Nicolas Dupont
License: MIT
Project-URL: Homepage, https://github.com/dupontcyborg/zpickle
Project-URL: Bug Tracker, https://github.com/dupontcyborg/zpickle/issues
Project-URL: Documentation, https://github.com/dupontcyborg/zpickle#readme
Project-URL: Source Code, https://github.com/dupontcyborg/zpickle
Keywords: pickle,compression,serialization,zstd,brotli,zlib,lzma,bzip2,lz4
Classifier: Intended Audience :: Developers
Classifier: License :: OSI Approved :: MIT License
Classifier: Programming Language :: Python :: 3
Classifier: Programming Language :: Python :: 3.10
Classifier: Programming Language :: Python :: 3.11
Classifier: Programming Language :: Python :: 3.12
Classifier: Programming Language :: Python :: 3.13
Classifier: Programming Language :: Python :: 3.14
Classifier: Topic :: Software Development :: Libraries :: Python Modules
Classifier: Topic :: System :: Archiving :: Compression
Classifier: Topic :: Software Development :: Libraries
Classifier: Operating System :: OS Independent
Requires-Python: >=3.10
License-File: LICENSE
Requires-Dist: compress-utils>=0.6.0
Dynamic: license-file
